{
  "version": 1,
  "updated_at": 1771291570,
  "entries": [
    {
      "report": "*PT BIZ - DAILY SMS SNAPSHOT*\nDate: Feb 16, 2026\nTime Range: 4:00 AM - 11:00 PM (America/Chicago)\n\n*Split By Line / Rep (Daily Window)*\n\n*Rep: Jack Licata*\n- Line: Jack's Personal Line (+1 817-580-9950)\n*Core Metrics*\n- Outbound Conversations: 67\n- Reply Rate: 7.5%\n- Bookings: 3\n- Opt Outs: 0\n\n*Revenue Signal*\n- Booking Rate Per Conversation: 4.5%\n- Booking Rate Per Reply: 60.0%\n- Rolling 7 Day Booking Per 100 Conversations: 7.8\n\n*Top Booking Driver*\n- Message Type: Opening Curiosity Hook\n- Reply Rate: 100.0%\n- Booking When Replied: 100.0%\n\n*Top Performing Sequence*\n- Cash Practice Field Manual\n- Conversations: 21\n- Bookings: 2\n- Reply Rate: 14.3%\n\n*Sequence Specific KPIs (Daily Window)*\n- Replies received counts unique contacts (max 1 reply per contact).\n- Cash Practice Field Manual: sent 41, replies received 3 (7.3% response rate), bookings 2 (66.7% close rate (2/3 replied)), opt-outs 0 (0.0%)\n- Raise Your Rates Cheatsheet: sent 17, replies received 0 (0.0% response rate), bookings 0 (n/a close rate (0 replies)), opt-outs 0 (0.0%)\n- Standalone Space Guide: sent 14, replies received 0 (0.0% response rate), bookings 0 (n/a close rate (0 replies)), opt-outs 0 (0.0%)\n- Workshop Playbook: sent 10, replies received 1 (10.0% response rate), bookings 0 (0.0% close rate (0/1 replied)), opt-outs 0 (0.0%)\n- Hiring Guide: sent 4, replies received 0 (0.0% response rate), bookings 0 (n/a close rate (0 replies)), opt-outs 0 (0.0%)\n- BOOK- BUYER Intro Flow: sent 2, replies received 0 (0.0% response rate), bookings 0 (n/a close rate (0 replies)), opt-outs 0 (0.0%)\n- No sequence (manual/direct): sent 5, replies received 1 (20.0% response rate), bookings 1 (100.0% close rate (1/1 replied)), opt-outs 0 (0.0%)\n\n*Risk Signal*\n- Sequence With Most Opt Outs: none\n- Opt Outs: 0\n- Opt Out Rate: 0.0%\n\n*Quick Take*\n- 3 bookings came from 67 outbound conversations; Cash Practice Field Manual led conversion; opt-out pressure stayed low.\n\n*Rep: Brandon Erwin*\n- Line: Jack's Personal Line (+1 817-580-9950)\n*Core Metrics*\n- Outbound Conversations: 5\n- Reply Rate: 0.0%\n- Bookings: 0\n- Opt Outs: 0\n\n*Revenue Signal*\n- Booking Rate Per Conversation: 0.0%\n- Booking Rate Per Reply: 0.0%\n- Rolling 7 Day Booking Per 100 Conversations: 0.0\n\n*Top Booking Driver*\n- Message Type: none found\n- Reply Rate: 0.0%\n- Booking When Replied: 0.0%\n\n*Top Performing Sequence*\n- none found\n\n*Sequence Specific KPIs (Daily Window)*\n- Replies received counts unique contacts (max 1 reply per contact).\n- Hiring Guide: sent 2, replies received 0 (0.0% response rate), bookings 0 (n/a close rate (0 replies)), opt-outs 0 (0.0%)\n- RAISE YOUR RATES CHEATSHEET: sent 1, replies received 0 (0.0% response rate), bookings 0 (n/a close rate (0 replies)), opt-outs 0 (0.0%)\n- Standalone Space Guide: sent 1, replies received 0 (0.0% response rate), bookings 0 (n/a close rate (0 replies)), opt-outs 0 (0.0%)\n- Workshop Playbook: sent 1, replies received 0 (0.0% response rate), bookings 0 (n/a close rate (0 replies)), opt-outs 0 (0.0%)\n\n*Risk Signal*\n- Sequence With Most Opt Outs: none\n- Opt Outs: 0\n- Opt Out Rate: 0.0%\n\n*Quick Take*\n- No bookings came from 5 outbound conversations; opt-out pressure stayed low.\n\n*Rep: Brandon Erwin*\n- Line: Brandon's personal line (+1 678-820-3770)\n*Core Metrics*\n- Outbound Conversations: 4\n- Reply Rate: 50.0%\n- Bookings: 0\n- Opt Outs: 0\n\n*Revenue Signal*\n- Booking Rate Per Conversation: 0.0%\n- Booking Rate Per Reply: 0.0%\n- Rolling 7 Day Booking Per 100 Conversations: 3.4\n\n*Top Booking Driver*\n- Message Type: Direct Call Invite\n- Reply Rate: 100.0%\n- Booking When Replied: 0.0%\n\n*Top Performing Sequence*\n- none found\n\n*Sequence Specific KPIs (Daily Window)*\n- Replies received counts unique contacts (max 1 reply per contact).\n- 5-Day Challenge: sent 1, replies received 1 (100.0% response rate), bookings 0 (0.0% close rate (0/1 replied)), opt-outs 0 (0.0%)\n- No sequence (manual/direct): sent 7, replies received 1 (14.3% response rate), bookings 0 (0.0% close rate (0/1 replied)), opt-outs 0 (0.0%)\n\n*Risk Signal*\n- Sequence With Most Opt Outs: none\n- Opt Outs: 0\n- Opt Out Rate: 0.0%\n\n*Quick Take*\n- No bookings came from 4 outbound conversations; opt-out pressure stayed low.",
      "runLabel": "Scheduled 4:00 PM",
      "ts": 1771304400
    },
    {
      "report": "*PT BIZ - DAILY SMS SNAPSHOT*\nDate: Feb 15, 2026\nTime Range: 4:00 AM - 11:00 PM (America/Chicago)\n\n*Split By Line / Rep (Daily Window)*\n\n*Rep: Jack Licata*\n- Line: Jack's Personal Line (+1 817-580-9950)\n*Core Metrics*\n- Outbound Conversations: 50\n- Reply Rate: 20.0%\n- Bookings: 2\n- Opt Outs: 1\n\n*Revenue Signal*\n- Booking Rate Per Conversation: 4.0%\n- Booking Rate Per Reply: 20.0%\n- Rolling 7 Day Booking Per 100 Conversations: 7.4\n\n*Top Booking Driver*\n- Message Type: Qualification Question\n- Reply Rate: 100.0%\n- Booking When Replied: 100.0%\n\n*Top Performing Sequence*\n- No sequence (manual/direct)\n- Conversations: 2\n- Bookings: 1\n- Reply Rate: 50.0%\n\n*Sequence Specific KPIs (Daily Window)*\n- Replies received counts unique contacts (max 1 reply per contact).\n- Cash Practice Field Manual: sent 23, replies received 1 (4.3% response rate), bookings 0 (0.0% close rate (0/1 replied)), opt-outs 0 (0.0%)\n- Raise Your Rates Cheatsheet: sent 17, replies received 3 (17.6% response rate), bookings 1 (33.3% close rate (1/3 replied)), opt-outs 0 (0.0%)\n- Standalone Space Guide: sent 10, replies received 2 (20.0% response rate), bookings 0 (0.0% close rate (0/2 replied)), opt-outs 1 (11.1%)\n- BOOK- BUYER Intro Flow: sent 4, replies received 1 (25.0% response rate), bookings 0 (0.0% close rate (0/1 replied)), opt-outs 0 (0.0%)\n- No sequence (manual/direct): sent 8, replies received 1 (12.5% response rate), bookings 1 (100.0% close rate (1/1 replied)), opt-outs 0 (0.0%)\n- Hiring Guide: sent 3, replies received 1 (33.3% response rate), bookings 0 (0.0% close rate (0/1 replied)), opt-outs 0 (0.0%)\n- Workshop Playbook: sent 2, replies received 0 (0.0% response rate), bookings 0 (n/a close rate (0 replies)), opt-outs 0 (0.0%)\n\n*Risk Signal*\n- Sequence With Most Opt Outs: Standalone Space Guide\n- Opt Outs: 1\n- Opt Out Rate: 11.1%\n\n*Quick Take*\n- 2 bookings came from 50 outbound conversations; No sequence (manual/direct) led conversion; Standalone Space Guide showed the highest opt-out pressure.\n\n*WEEK TO DATE SUMMARY*\n- Total Conversations: 68\n- Average Reply Rate: 23.5%\n- Total Bookings: 5\n- Highest Converting Structure: Qualification Question (100.0% booking when replied)\n- Highest Converting Sequence: Cash-Based PT HIRING GUIDE (100.0% booking per conversation)\n- Sequence With Highest Opt Out Rate: Hiring Guide (50.0%)\n\n*Rep: Brandon Erwin*\n- Line: Brandon's personal line (+1 678-820-3770)\n*Core Metrics*\n- Outbound Conversations: 3\n- Reply Rate: 33.3%\n- Bookings: 0\n- Opt Outs: 0\n\n*Revenue Signal*\n- Booking Rate Per Conversation: 0.0%\n- Booking Rate Per Reply: 0.0%\n- Rolling 7 Day Booking Per 100 Conversations: 3.7\n\n*Top Booking Driver*\n- Message Type: Follow-Up Reminder\n- Reply Rate: 50.0%\n- Booking When Replied: 0.0%\n\n*Top Performing Sequence*\n- none found\n\n*Sequence Specific KPIs (Daily Window)*\n- Replies received counts unique contacts (max 1 reply per contact).\n- 5-Day Challenge: sent 3, replies received 1 (33.3% response rate), bookings 0 (0.0% close rate (0/1 replied)), opt-outs 0 (0.0%)\n\n*Risk Signal*\n- Sequence With Most Opt Outs: none\n- Opt Outs: 0\n- Opt Out Rate: 0.0%\n\n*Quick Take*\n- No bookings came from 3 outbound conversations; opt-out pressure stayed low.\n\n*WEEK TO DATE SUMMARY*\n- Total Conversations: 27\n- Average Reply Rate: 11.1%\n- Total Bookings: 1\n- Highest Converting Structure: Follow-Up Reminder (0.0% booking when replied)\n- Highest Converting Sequence: No sequence (manual/direct) (4.2% booking per conversation)\n- Sequence With Highest Opt Out Rate: No sequence (manual/direct) (4.2%)",
      "runLabel": "Scheduled 4:00 PM",
      "ts": 1771218000
    },
    {
      "report": "*PT BIZ - DAILY SMS SNAPSHOT*\nDate: Feb 14, 2026\nTime Range: 4:00 AM - 11:00 PM (America/Chicago)\n\n*Split By Line / Rep (Daily Window)*\n\n*Rep: Jack Licata*\n- Line: Jack's Personal Line (+1 817-580-9950)\n*Core Metrics*\n- Outbound Conversations: 29\n- Reply Rate: 24.1%\n- Bookings: 3\n- Opt Outs: 0\n\n*Revenue Signal*\n- Booking Rate Per Conversation: 10.3%\n- Booking Rate Per Reply: 42.9%\n- Rolling 7 Day Booking Per 100 Conversations: 10.3\n\n*Top Booking Driver*\n- Message Type: Follow-Up Reminder\n- Reply Rate: 13.3%\n- Booking When Replied: 50.0%\n\n*Top Performing Sequence*\n- Cash-Based PT HIRING GUIDE\n- Conversations: 1\n- Bookings: 1\n- Reply Rate: 100.0%\n\n*Sequence Specific KPIs (Daily Window)*\n- Replies received counts unique contacts (max 1 reply per contact).\n- BOOK- BUYER Intro Flow: sent 12, replies received 1 (8.3% response rate), bookings 1 (100.0% close rate (1/1 replied)), opt-outs 0 (0.0%)\n- No sequence (manual/direct): sent 15, replies received 4 (26.7% response rate), bookings 1 (25.0% close rate (1/4 replied)), opt-outs 0 (0.0%)\n- WORKSHOP PLAYBOOK: sent 5, replies received 1 (20.0% response rate), bookings 0 (0.0% close rate (0/1 replied)), opt-outs 0 (0.0%)\n- RAISE YOUR RATES CHEATSHEET: sent 4, replies received 0 (0.0% response rate), bookings 0 (n/a close rate (0 replies)), opt-outs 0 (0.0%)\n- Cash Practice Field Manual: sent 3, replies received 0 (0.0% response rate), bookings 0 (n/a close rate (0 replies)), opt-outs 0 (0.0%)\n- STANDALONE SPACE GUIDE: sent 2, replies received 0 (0.0% response rate), bookings 0 (n/a close rate (0 replies)), opt-outs 0 (0.0%)\n- Cash-Based PT HIRING GUIDE: sent 9, replies received 1 (11.1% response rate), bookings 1 (100.0% close rate (1/1 replied)), opt-outs 0 (0.0%)\n\n*Risk Signal*\n- Sequence With Most Opt Outs: none\n- Opt Outs: 0\n- Opt Out Rate: 0.0%\n\n*Quick Take*\n- 3 bookings came from 29 outbound conversations; Cash-Based PT HIRING GUIDE led conversion; opt-out pressure stayed low.\n\n*Rep: Brandon Erwin*\n- Line: Brandon's personal line (+1 678-820-3770)\n*Core Metrics*\n- Outbound Conversations: 26\n- Reply Rate: 7.7%\n- Bookings: 1\n- Opt Outs: 1\n\n*Revenue Signal*\n- Booking Rate Per Conversation: 3.8%\n- Booking Rate Per Reply: 50.0%\n- Rolling 7 Day Booking Per 100 Conversations: 3.8\n\n*Top Booking Driver*\n- Message Type: none found\n- Reply Rate: 0.0%\n- Booking When Replied: 0.0%\n\n*Top Performing Sequence*\n- No sequence (manual/direct)\n- Conversations: 24\n- Bookings: 1\n- Reply Rate: 8.3%\n\n*Sequence Specific KPIs (Daily Window)*\n- Replies received counts unique contacts (max 1 reply per contact).\n- No sequence (manual/direct): sent 27, replies received 2 (7.4% response rate), bookings 1 (50.0% close rate (1/2 replied)), opt-outs 1 (4.2%)\n- 5-Day Challenge: sent 2, replies received 0 (0.0% response rate), bookings 0 (n/a close rate (0 replies)), opt-outs 0 (0.0%)\n\n*Risk Signal*\n- Sequence With Most Opt Outs: No sequence (manual/direct)\n- Opt Outs: 1\n- Opt Out Rate: 4.2%\n\n*Quick Take*\n- 1 booking came from 26 outbound conversations; No sequence (manual/direct) led conversion; No sequence (manual/direct) showed the highest opt-out pressure.",
      "runLabel": "Scheduled 4:00 PM",
      "ts": 1771131600
    }
  ]
}
